portablemc_fabric/__init__.py
portablemc_fabric-2.0.1.dist-info/WHEEL
portablemc_fabric-2.0.1.dist-info/METADATA
portablemc_fabric-2.0.1.dist-info/RECORD
