Metadata-Version: 2.1
Name: portablemc-fabric
Version: 2.0.1
Summary: Start Minecraft using the Fabric mod loader using '<exec> start fabric:[<mc-version>[:<loader-version>]]'.
License: GPL-3.0-only
Author: Théo Rozier
Author-email: contact@theorozier.fr
Requires-Python: >=3.6
Classifier: License :: OSI Approved :: GNU General Public License v3 (GPLv3)
Classifier: Programming Language :: Python :: 3
Classifier: Programming Language :: Python :: 3.6
Classifier: Programming Language :: Python :: 3.7
Classifier: Programming Language :: Python :: 3.8
Classifier: Programming Language :: Python :: 3.9
Classifier: Programming Language :: Python :: 3.10
Requires-Dist: portablemc (>=3,<4)
